asingleton/__init__.py
asingleton/asingleton.py
asingleton-0.3.0.dist-info/LICENSE
asingleton-0.3.0.dist-info/METADATA
asingleton-0.3.0.dist-info/WHEEL
asingleton-0.3.0.dist-info/top_level.txt
asingleton-0.3.0.dist-info/RECORD
