Metadata-Version: 2.1
Name: asingleton
Version: 0.3.0
Summary: singleton(cls, [attr_name,] [disable_name_mangling,] [not_just_this_class,]) is cls
Home-page: https://github.com/guallo/asingleton
Author: The asingleton Authors
Author-email: guallo.username@gmail.com
License: UNKNOWN
Platform: UNKNOWN
Classifier: Programming Language :: Python :: 3
Classifier: License :: OSI Approved :: MIT License
Classifier: Operating System :: OS Independent
Requires-Python: >=3.6
